nonebot_plugin_anime_trace/__init__.py
nonebot_plugin_anime_trace/api.py
nonebot_plugin_anime_trace/config.py
nonebot_plugin_anime_trace/model.py
nonebot_plugin_anime_trace/tool.py
nonebot_plugin_anime_trace-0.2.3.dist-info/LICENSE
nonebot_plugin_anime_trace-0.2.3.dist-info/METADATA
nonebot_plugin_anime_trace-0.2.3.dist-info/WHEEL
nonebot_plugin_anime_trace-0.2.3.dist-info/RECORD
