Metadata-Version: 2.3
Name: nonebot-plugin-anime-trace
Version: 0.2.3
Summary: 通过ai.animedb.cn的api识别动漫、galgame角色
License: MIT
Author: 友利奈绪-勿忘我
Author-email: 1520872279@qq.com
Requires-Python: >=3.10,<4.0
Classifier: License :: OSI Approved :: MIT License
Classifier: Programming Language :: Python :: 3
Classifier: Programming Language :: Python :: 3.10
Classifier: Programming Language :: Python :: 3.11
Classifier: Programming Language :: Python :: 3.12
Classifier: Programming Language :: Python :: 3.13
Requires-Dist: httpx (>=0.24.0)
Requires-Dist: naotool (>=0.3.4)
Requires-Dist: nonebot-adapter-onebot (>=2.2.3)
Requires-Dist: nonebot2 (>=2.0.0)
Requires-Dist: pillow (>=9.5.0)
Project-URL: Documentation, https://github.com/tomorinao-www/nonebot-plugin-anime-trace#README.md
Project-URL: Homepage, https://github.com/tomorinao-www/nonebot-plugin-anime-trace
Project-URL: Repository, https://github.com/tomorinao-www/nonebot-plugin-anime-trace
